LICENSE
MANIFEST.in
README.md
setup.py
tests/__init__.py
xlf_merge/XlfParser.py
xlf_merge/__init__.py
xlf_merge/__main__.py
xlf_merge.egg-info/PKG-INFO
xlf_merge.egg-info/SOURCES.txt
xlf_merge.egg-info/dependency_links.txt
xlf_merge.egg-info/entry_points.txt
xlf_merge.egg-info/requires.txt
xlf_merge.egg-info/top_level.txt
xlf_merge/bin/__init__.py
xlf_merge/bin/xlf_merge.py