Metadata-Version: 2.1
Name: xlf-merge
Version: 0.1.6
Summary: APP for merging xlf translation files
Home-page: https://github.com/Salamek/xlf-merge
Author: Adam Schubert
Author-email: adam.schubert@sg1-game.net
License: GPL-3.0 
Project-URL: Release notes, https://github.com/Salamek/xlf-merge/releases
Classifier: Development Status :: 5 - Production/Stable
Classifier: Environment :: Console
Classifier: Intended Audience :: Developers
Classifier: License :: OSI Approved :: GNU General Public License v3 (GPLv3)
Classifier: Operating System :: OS Independent
Classifier: Programming Language :: Python
Classifier: Programming Language :: Python :: 3
Classifier: Programming Language :: Python :: 3.4
Classifier: Programming Language :: Python :: 3.5
Classifier: Programming Language :: Python :: 3.6
Classifier: Programming Language :: Python :: 3.7
Classifier: Programming Language :: Python :: 3.8
Classifier: Topic :: Software Development
Requires-Python: >=3.4
License-File: LICENSE
